pymetrc/__init__.py
pymetrc/apicaller.py
pymetrc/endpoints.json
pymetrc/pymetrc.py
pymetrc/ratelimiter.py
pymetrc-0.2.2.dist-info/LICENSE
pymetrc-0.2.2.dist-info/METADATA
pymetrc-0.2.2.dist-info/WHEEL
pymetrc-0.2.2.dist-info/top_level.txt
pymetrc-0.2.2.dist-info/RECORD
