Metadata-Version: 2.1
Name: pymetrc
Version: 0.2.2
Summary: For interacting with the Metrc API
Home-page: https://gitlab.com/kevstewa/pymetrc
Author: Kevin A Stewart
Author-email: kevstewa@protonmail.com
License: UNKNOWN
Platform: UNKNOWN
Classifier: Programming Language :: Python :: 3
Classifier: License :: OSI Approved :: GNU Affero General Public License v3
Classifier: Operating System :: OS Independent
Requires-Python: >=3.7
License-File: LICENSE
Requires-Dist: aiohttp (>=3.7.4.post0)
Requires-Dist: tqdm (>=4.62.3)
